peempy/__init__.py
peempy/aligner.py
peempy/datawatcher.py
peempy/fileproc.py
peempy/graphics.py
peempy/imageproc.py
peempy/imgstack.py
peempy/paths.py
peempy/peembatch.py
peempy/utils.py
peempy/videofig.py
peempy/xmcd.py
peempy/cmdline/__init__.py
peempy/cmdline/cmd_batch.py
peempy/cmdline/cmd_peemcli.py
peempy/cmdline/cmd_xmcd.py
peempy/cmdline/utils.py
peempy/tests/__init__.py
peempy/tests/conftest.py
peempy/tests/mock_xmcd.py
peempy/tests/test_crop_region.py
peempy/tests/test_imageproc.py
peempy/tests/test_imgstack.py
peempy/tests/test_xmcd.py
peempy-0.2.0.dist-info/LICENSE
peempy-0.2.0.dist-info/METADATA
peempy-0.2.0.dist-info/WHEEL
peempy-0.2.0.dist-info/entry_points.txt
peempy-0.2.0.dist-info/top_level.txt
peempy-0.2.0.dist-info/RECORD
