Metadata-Version: 2.1
Name: peempy
Version: 0.2.0
Summary: Python tool for processing XMCD PEEM data
Home-page: https://gitlab.com/bz1/peempy
Author: Bonan Zhu
Author-email: bon.zhu@protonmail.com
License: MIT License
Platform: UNKNOWN
Classifier: Programming Language :: Python
Classifier: Development Status :: 5 - Production/Stable
Requires-Dist: matplotlib
Requires-Dist: colorcet
Requires-Dist: scikit-image
Requires-Dist: tqdm
Requires-Dist: scipy
Requires-Dist: numpy
Requires-Dist: click
Provides-Extra: pre-commit
Requires-Dist: pre-commit ; extra == 'pre-commit'
Requires-Dist: yapf ; extra == 'pre-commit'
Provides-Extra: testing
Requires-Dist: pytest ; extra == 'testing'
